{
 "version": 1,
 "meta": {
  "song_file": "music.mp3",
  "title": "Party Rock Anthem (auto)",
  "bpm": 130.002,
  "anchor_ms": 158900.0,
  "duration_ms": 260342.1,
  "audio_latency_ms": 300,
  "laser_lead_ms": 3900,
  "strobe_lead_ms": 6500,
  "preroll_fog_ms": 20000
 },
 "cues": [
  {
   "t0": 0,
   "t1": 5000,
   "fx": "solid",
   "p": {
    "color": "white"
   }
  },
  {
   "t0": 5000,
   "t1": 20000,
   "fx": "intro_gradient",
   "p": {}
  },
  {
   "t0": 20000,
   "t1": 43209.2,
   "fx": "circle_tick",
   "p": {
    "hue": 0.0,
    "v": 0.08,
    "decay": 120,
    "decke": [
     0.08,
     0.7,
     0.1,
     200
    ]
   }
  },
  {
   "t0": 43209.2,
   "t1": 52009.2,
   "fx": "upulse",
   "p": {
    "grid": "beat",
    "domain": [
     43209.22601190752,
     59209.22601190752
    ],
    "decay": [
     140,
     60
    ],
    "vmax": [
     0.2,
     0.6
    ],
    "hue": {
     "mode": "beat_cycle",
     "step": 0.13
    }
   }
  },
  {
   "t0": 52009.2,
   "t1": 58309.2,
   "fx": "upulse",
   "p": {
    "grid": "eighth",
    "domain": [
     43209.22601190752,
     59209.22601190752
    ],
    "decay": [
     100,
     40
    ],
    "vmax": [
     0.45,
     0.9
    ],
    "sat": [
     1.0,
     0.4
    ],
    "hue": {
     "mode": "beat_cycle",
     "step": 0.13
    }
   }
  },
  {
   "t0": 58309.2,
   "t1": 59209.2,
   "fx": "roll",
   "p": {
    "p0": 230,
    "slope": 140,
    "ref_dur": 900,
    "pmin": 80,
    "width": 40
   }
  },
  {
   "t0": 59209.2,
   "t1": 66593.7,
   "fx": "stutter_pulse",
   "p": {
    "hit": 59209.22601190752,
    "windows": [
     [
      0,
      40
     ],
     [
      80,
      120
     ],
     [
      160,
      200
     ]
    ],
    "colors": [
     "white",
     [
      0.95,
      1.0,
      1.0
     ]
    ]
   }
  },
  {
   "t0": 66593.7,
   "t1": 72747.2,
   "fx": "chase",
   "p": {
    "hue": 0.62,
    "v_head": 0.45,
    "v_trail": 0.12,
    "decay": 220
   }
  },
  {
   "t0": 72747.2,
   "t1": 81547.2,
   "fx": "upulse",
   "p": {
    "grid": "beat",
    "domain": [
     72747.23311949047,
     88747.23311949047
    ],
    "decay": [
     140,
     60
    ],
    "vmax": [
     0.2,
     0.6
    ],
    "hue": {
     "mode": "beat_cycle",
     "step": 0.13
    }
   }
  },
  {
   "t0": 81547.2,
   "t1": 87847.2,
   "fx": "upulse",
   "p": {
    "grid": "eighth",
    "domain": [
     72747.23311949047,
     88747.23311949047
    ],
    "decay": [
     100,
     40
    ],
    "vmax": [
     0.45,
     0.9
    ],
    "sat": [
     1.0,
     0.4
    ],
    "hue": {
     "mode": "beat_cycle",
     "step": 0.13
    }
   }
  },
  {
   "t0": 87847.2,
   "t1": 88747.2,
   "fx": "roll",
   "p": {
    "p0": 230,
    "slope": 140,
    "ref_dur": 900,
    "pmin": 80,
    "width": 40
   }
  },
  {
   "t0": 88747.2,
   "t1": 96131.7,
   "fx": "gated_pulse",
   "p": {
    "hit": 88747.23311949047,
    "bar_anchor": 88747.23311949047,
    "grid": "eighth",
    "width": 60,
    "v": 1.0,
    "hues": [
     0.87,
     0.5
    ],
    "color_by": "pulse",
    "strobe_mod": [
     4,
     [
      3
     ]
    ],
    "strobe": {
     "v": 0.9,
     "ceiling": 0.2
    }
   }
  },
  {
   "t0": 96131.7,
   "t1": 98417.8,
   "fx": "gated_pulse",
   "p": {
    "bar_anchor": 96131.73489638622,
    "grid": "beat",
    "width": 100,
    "v": 0.9,
    "hues": [
     0.13,
     0.87
    ],
    "white_slam": true
   }
  },
  {
   "t0": 98417.8,
   "t1": 102285.2,
   "fx": "circle_tick",
   "p": {
    "hue": 0.0,
    "v": 0.08,
    "decay": 120,
    "decke": [
     0.08,
     0.7,
     0.1,
     200
    ]
   }
  },
  {
   "t0": 102285.2,
   "t1": 111085.2,
   "fx": "upulse",
   "p": {
    "grid": "beat",
    "domain": [
     102285.24022707343,
     118285.24022707343
    ],
    "decay": [
     140,
     60
    ],
    "vmax": [
     0.2,
     0.6
    ],
    "hue": {
     "mode": "beat_cycle",
     "step": 0.13
    }
   }
  },
  {
   "t0": 111085.2,
   "t1": 117385.2,
   "fx": "upulse",
   "p": {
    "grid": "eighth",
    "domain": [
     102285.24022707343,
     118285.24022707343
    ],
    "decay": [
     100,
     40
    ],
    "vmax": [
     0.45,
     0.9
    ],
    "sat": [
     1.0,
     0.4
    ],
    "hue": {
     "mode": "beat_cycle",
     "step": 0.13
    }
   }
  },
  {
   "t0": 117385.2,
   "t1": 118285.2,
   "fx": "roll",
   "p": {
    "p0": 230,
    "slope": 140,
    "ref_dur": 900,
    "pmin": 80,
    "width": 40
   }
  },
  {
   "t0": 118285.2,
   "t1": 125669.7,
   "fx": "gated_pulse",
   "p": {
    "hit": 118285.24022707343,
    "bar_anchor": 118285.24022707343,
    "grid": "beat",
    "width": 110,
    "v": 1.0,
    "hues": [
     0.75,
     0.5
    ],
    "strobe_mod": [
     8,
     [
      4
     ]
    ],
    "strobe": {
     "v": 0.9
    }
   }
  },
  {
   "t0": 125669.7,
   "t1": 131762.0,
   "fx": "upulse",
   "p": {
    "grid": "beat",
    "domain": [
     125669.74200396916,
     136746.4946693128
    ],
    "decay": [
     140,
     60
    ],
    "vmax": [
     0.2,
     0.6
    ],
    "hue": {
     "mode": "beat_cycle",
     "step": 0.13
    }
   }
  },
  {
   "t0": 131762.0,
   "t1": 135846.5,
   "fx": "upulse",
   "p": {
    "grid": "eighth",
    "domain": [
     125669.74200396916,
     136746.4946693128
    ],
    "decay": [
     100,
     40
    ],
    "vmax": [
     0.45,
     0.9
    ],
    "sat": [
     1.0,
     0.4
    ],
    "hue": {
     "mode": "beat_cycle",
     "step": 0.13
    }
   }
  },
  {
   "t0": 135846.5,
   "t1": 136746.5,
   "fx": "roll",
   "p": {
    "p0": 230,
    "slope": 140,
    "ref_dur": 900,
    "pmin": 80,
    "width": 40
   }
  },
  {
   "t0": 136746.5,
   "t1": 144131.0,
   "fx": "stutter_pulse",
   "p": {
    "hit": 136746.4946693128,
    "windows": [
     [
      0,
      40
     ],
     [
      80,
      120
     ],
     [
      160,
      200
     ]
    ],
    "colors": [
     "white",
     [
      0.95,
      1.0,
      1.0
     ]
    ]
   }
  },
  {
   "t0": 144131.0,
   "t1": 152253.9,
   "fx": "upulse",
   "p": {
    "grid": "beat",
    "domain": [
     144130.99644620853,
     158900.0
    ],
    "decay": [
     140,
     60
    ],
    "vmax": [
     0.2,
     0.6
    ],
    "hue": {
     "mode": "beat_cycle",
     "step": 0.13
    }
   }
  },
  {
   "t0": 152253.9,
   "t1": 158000.0,
   "fx": "upulse",
   "p": {
    "grid": "eighth",
    "domain": [
     144130.99644620853,
     158900.0
    ],
    "decay": [
     100,
     40
    ],
    "vmax": [
     0.45,
     0.9
    ],
    "sat": [
     1.0,
     0.4
    ],
    "hue": {
     "mode": "beat_cycle",
     "step": 0.13
    }
   }
  },
  {
   "t0": 158000.0,
   "t1": 158900.0,
   "fx": "roll",
   "p": {
    "p0": 230,
    "slope": 140,
    "ref_dur": 900,
    "pmin": 80,
    "width": 40
   }
  },
  {
   "t0": 158900.0,
   "t1": 166284.5,
   "fx": "hit_black",
   "p": {
    "hit": 158900.0
   }
  },
  {
   "t0": 166284.5,
   "t1": 180284.0,
   "fx": "chase",
   "p": {
    "hue": 0.62,
    "v_head": 0.45,
    "v_trail": 0.12,
    "decay": 220
   }
  },
  {
   "t0": 180284.0,
   "t1": 189084.0,
   "fx": "upulse",
   "p": {
    "grid": "beat",
    "domain": [
     180284.04024553468,
     196284.04024553468
    ],
    "decay": [
     140,
     60
    ],
    "vmax": [
     0.2,
     0.6
    ],
    "hue": {
     "mode": "beat_cycle",
     "step": 0.13
    }
   }
  },
  {
   "t0": 189084.0,
   "t1": 195384.0,
   "fx": "upulse",
   "p": {
    "grid": "eighth",
    "domain": [
     180284.04024553468,
     196284.04024553468
    ],
    "decay": [
     100,
     40
    ],
    "vmax": [
     0.45,
     0.9
    ],
    "sat": [
     1.0,
     0.4
    ],
    "hue": {
     "mode": "beat_cycle",
     "step": 0.13
    }
   }
  },
  {
   "t0": 195384.0,
   "t1": 196284.0,
   "fx": "roll",
   "p": {
    "p0": 230,
    "slope": 140,
    "ref_dur": 900,
    "pmin": 80,
    "width": 40
   }
  },
  {
   "t0": 196284.0,
   "t1": 211053.0,
   "fx": "gated_pulse",
   "p": {
    "hit": 196284.04024553468,
    "bar_anchor": 196284.04024553468,
    "grid": "beat",
    "width": 110,
    "v": 1.0,
    "hues": [
     0.75,
     0.5
    ],
    "strobe_mod": [
     8,
     [
      4
     ]
    ],
    "strobe": {
     "v": 0.9
    }
   }
  },
  {
   "t0": 213052.8,
   "t1": 221852.8,
   "fx": "upulse",
   "p": {
    "grid": "beat",
    "domain": [
     213052.76688050953,
     229052.76688050953
    ],
    "decay": [
     140,
     60
    ],
    "vmax": [
     0.2,
     0.6
    ],
    "hue": {
     "mode": "beat_cycle",
     "step": 0.13
    }
   }
  },
  {
   "t0": 221852.8,
   "t1": 228152.8,
   "fx": "upulse",
   "p": {
    "grid": "eighth",
    "domain": [
     213052.76688050953,
     229052.76688050953
    ],
    "decay": [
     100,
     40
    ],
    "vmax": [
     0.45,
     0.9
    ],
    "sat": [
     1.0,
     0.4
    ],
    "hue": {
     "mode": "beat_cycle",
     "step": 0.13
    }
   }
  },
  {
   "t0": 228152.8,
   "t1": 229052.8,
   "fx": "roll",
   "p": {
    "p0": 230,
    "slope": 140,
    "ref_dur": 900,
    "pmin": 80,
    "width": 40
   }
  },
  {
   "t0": 229052.8,
   "t1": 236437.3,
   "fx": "stutter_pulse",
   "p": {
    "hit": 229052.76688050953,
    "windows": [
     [
      0,
      40
     ],
     [
      80,
      120
     ],
     [
      160,
      200
     ]
    ],
    "colors": [
     "white",
     [
      0.95,
      1.0,
      1.0
     ]
    ]
   }
  },
  {
   "t0": 236437.3,
   "t1": 243786.3,
   "fx": "gated_pulse",
   "p": {
    "bar_anchor": 236437.26865740528,
    "grid": "beat",
    "width": 100,
    "v": 0.9,
    "hues": [
     0.5,
     0.87
    ],
    "white_slam": true
   }
  },
  {
   "t0": 243786.3,
   "t1": 258642.1,
   "fx": "circle_tick",
   "p": {
    "hue": 0.0,
    "v": 0.08,
    "decay": 120,
    "decke": [
     0.08,
     0.7,
     0.1,
     200
    ]
   }
  },
  {
   "t0": 258642.1,
   "t1": 260342.1,
   "fx": "outro_fade",
   "p": {
    "dur": 1700.0
   }
  }
 ],
 "accents": [
  [
   150.9,
   0.88
  ],
  [
   2914.1,
   0.83
  ],
  [
   3610.7,
   0.82
  ],
  [
   4527.9,
   0.81
  ],
  [
   5201.3,
   0.89
  ],
  [
   5921.1,
   0.8
  ],
  [
   6606.1,
   0.93
  ],
  [
   7302.7,
   0.86
  ],
  [
   11598.4,
   0.85
  ],
  [
   12283.4,
   0.83
  ],
  [
   13305.0,
   0.79
  ],
  [
   59025.1,
   0.91
  ],
  [
   74919.2,
   0.88
  ],
  [
   75836.4,
   0.8
  ]
 ],
 "devices": {
  "fog": [
   [
    0,
    5000
   ],
   [
    49209.2,
    66593.7
   ],
   [
    78747.2,
    98417.8
   ],
   [
    108285.2,
    144131.0
   ],
   [
    148900.0,
    166284.5
   ],
   [
    186284.0,
    204284.0
   ],
   [
    219052.8,
    242437.3
   ]
  ],
  "laser": [
   [
    59209.2,
    66593.7
   ],
   [
    136746.5,
    144131.0
   ],
   [
    166284.5,
    170284.5
   ],
   [
    229052.8,
    236437.3
   ]
  ],
  "strobe": [
   [
    59209.2,
    66593.7
   ],
   [
    88747.2,
    96131.7
   ],
   [
    118285.2,
    125669.7
   ],
   [
    136746.5,
    144131.0
   ],
   [
    158900.0,
    166284.5
   ],
   [
    196284.0,
    211053.0
   ],
   [
    229052.8,
    236437.3
   ]
  ]
 }
}
